{
  "backend/main.mo": "Defines MCQ types, topics, and difficulties, initializes an empty question bank, and populates it with multiple Russian Revolution–related questions.",
  "feature_evidence.json": "Empty feature evidence report structure with no listed features.",
  "frontend-file-summaries.txt": "Prewritten summaries of major frontend files including components, hooks, styles, and Tailwind config.",
  "frontend/index.css": "Tailwind base and theme variables defining a set of color tokens for light and dark modes.",
  "frontend/index.html": "HTML entry point loading the React app with a root div and main script.",
  "frontend/src/App.tsx": "Main quiz UI managing start, question, and results screens with navigation and progress display.",
  "frontend/src/hooks/useActor.ts": "Creates and manages a backend actor based on Internet Identity, refreshing queries when the identity changes.",
  "frontend/src/hooks/useInternetIdentity.ts": "Implements Internet Identity context, login flow, state handling, and identity persistence.",
  "frontend/src/hooks/useQueries.ts": "React Query hooks to fetch MCQs and submit quiz answers through the backend actor.",
  "frontend/src/hooks/useQuiz.ts": "Controls quiz logic: ordering questions, tracking answers, navigation, and submitting for scoring.",
  "frontend/src/index.css": "Tailwind theme with warm vintage color palette for light and dark modes plus base styling.",
  "frontend/src/main.tsx": "Bootstraps React app with QueryClient and InternetIdentityProvider wrappers.",
  "frontend/tailwind.config.js": "Tailwind CSS config enabling dark mode, custom OKLCH color tokens, extended theme utilities, and typography/container/animation plugins.",
  "project_state.json": "Project metadata describing existing IC app features and pending MCQ-related feature requests with versioned state."
}